scalexi_llm/__init__.py
scalexi_llm/scalexi_llm.py
scalexi_llm-0.1.11.dist-info/METADATA
scalexi_llm-0.1.11.dist-info/WHEEL
scalexi_llm-0.1.11.dist-info/top_level.txt
scalexi_llm-0.1.11.dist-info/RECORD
