Metadata-Version: 2.4
Name: scalexi_llm
Version: 0.1.11
Summary: A comprehensive multi-provider LLM proxy library with unified interface
Home-page: https://github.com/scalexi/scalexi_llm
Author: scalex_innovation
Author-email: scalex_innovation@gmail.com
Keywords: llm,ai,openai,anthropic,gemini,groq,deepseek,grok,qwen,ollama,exa,proxy,api
Classifier: Development Status :: 3 - Alpha
Classifier: Intended Audience :: Developers
Classifier: License :: OSI Approved :: MIT License
Classifier: Programming Language :: Python :: 3
Classifier: Programming Language :: Python :: 3.8
Classifier: Programming Language :: Python :: 3.9
Classifier: Programming Language :: Python :: 3.10
Classifier: Programming Language :: Python :: 3.11
Classifier: Programming Language :: Python :: 3.12
Classifier: Programming Language :: Python :: 3.13
Requires-Python: >=3.8
Requires-Dist: openai
Requires-Dist: anthropic
Requires-Dist: google-genai
Requires-Dist: groq
Requires-Dist: pymupdf
Requires-Dist: xai-sdk
Requires-Dist: python-docx
Requires-Dist: pydantic
Requires-Dist: python-dotenv
Requires-Dist: exa-py
Requires-Dist: google-search-results
Dynamic: author
Dynamic: author-email
Dynamic: classifier
Dynamic: description
Dynamic: description-content-type
Dynamic: home-page
Dynamic: keywords
Dynamic: requires-dist
Dynamic: requires-python
Dynamic: summary
